agent_path/__init__.py
agent_path/llm.py
agent_path/recursive.py
agent_path/utils.py
agent_path-0.1.2.dist-info/METADATA
agent_path-0.1.2.dist-info/WHEEL
agent_path-0.1.2.dist-info/top_level.txt
agent_path-0.1.2.dist-info/RECORD
