Metadata-Version: 2.1
Name: agent_path
Version: 0.1.2
Summary: Default template for PDM package
Author-email: Yanli <mail@yanli.one>
License: Apache-2.0
Requires-Python: >=3.10
Requires-Dist: llama-index-core >=0.10.30
Requires-Dist: llama-index-llms-openai >=0.1.16
Requires-Dist: jinja2 >=3.1.3
Requires-Dist: llama-index-agent-openai >=0.2.2
Requires-Dist: python-dotenv >=1.0.1
Requires-Dist: fancy-printer ==0.1
